PM3/__init__.py
PM3/app.py
PM3/cli.py
PM3/cron_checker.py
PM3/libs/pm3table.py
PM3/libs/system_scripts.py
PM3/model/pm3_protocol.py
PM3/model/process.py
pm3-0.4.4.dist-info/licenses/LICENSE
pm3-0.4.4.dist-info/METADATA
pm3-0.4.4.dist-info/WHEEL
pm3-0.4.4.dist-info/entry_points.txt
pm3-0.4.4.dist-info/top_level.txt
pm3-0.4.4.dist-info/RECORD
