Metadata-Version: 2.4
Name: PM3
Version: 0.4.4
Summary: Like pm2 without node.js ;-)
Author-email: Ilario Febi <i.febi@febi.biz>
Keywords: PM3
Classifier: Framework :: Flask
Classifier: Programming Language :: Python :: 3
Requires-Python: >=3.9
License-File: LICENSE
Requires-Dist: argcomplete>=2.0.0
Requires-Dist: dsnparse>=0.1.0
Requires-Dist: Flask>=2.0.0
Requires-Dist: pendulum>=2.1.0
Requires-Dist: psutil>=5.9.0
Requires-Dist: pydantic>=2.0.0
Requires-Dist: requests>=2.26.0
Requires-Dist: rich>=10.0.0
Requires-Dist: tinydb>=4.7.0
Requires-Dist: pytailer>=0.1.0
Dynamic: license-file
